Metadata-Version: 1.0
Name: agent-reporting
Version: 0.0.1
Summary: Agent Reporting
Home-page: UNKNOWN
Author: UNKNOWN
Author-email: UNKNOWN
License: __license__
Platform: UNKNOWN
